pygan/__init__.py
pygan/discriminative_model.py
pygan/ebaae_image_generator.py
pygan/ebgan_image_generator.py
pygan/feature_matching.py
pygan/gan_image_generator.py
pygan/gans_value_function.py
pygan/generative_adversarial_networks.py
pygan/generative_model.py
pygan/noise_sampler.py
pygan/true_sampler.py
pygan/discriminativemodel/__init__.py
pygan/discriminativemodel/auto_encoder_model.py
pygan/discriminativemodel/cnn_model.py
pygan/discriminativemodel/encoder_decoder_model.py
pygan/discriminativemodel/lstm_model.py
pygan/discriminativemodel/nn_model.py
pygan/discriminativemodel/autoencodermodel/__init__.py
pygan/discriminativemodel/autoencodermodel/convolutional_auto_encoder.py
pygan/discriminativemodel/autoencodermodel/encoder_decoder_model.py
pygan/discriminativemodel/autoencodermodel/convolutionalautoencoder/__init__.py
pygan/discriminativemodel/autoencodermodel/convolutionalautoencoder/convolutional_ladder_networks.py
pygan/discriminativemodel/autoencodermodel/convolutionalautoencoder/seq_cae_model.py
pygan/discriminativemodel/autoencodermodel/convolutionalautoencoder/convolutionalladdernetworks/__init__.py
pygan/discriminativemodel/autoencodermodel/convolutionalautoencoder/convolutionalladdernetworks/seq_cln_model.py
pygan/discriminativemodel/cnnmodel/__init__.py
pygan/discriminativemodel/cnnmodel/seq_cnn_model.py
pygan/featurematching/__init__.py
pygan/featurematching/denoising_feature_matching.py
pygan/gansvaluefunction/__init__.py
pygan/gansvaluefunction/margin_loss.py
pygan/gansvaluefunction/mini_max.py
pygan/generativeadversarialnetworks/__init__.py
pygan/generativeadversarialnetworks/adversarial_auto_encoders.py
pygan/generativemodel/__init__.py
pygan/generativemodel/auto_encoder_model.py
pygan/generativemodel/cnn_model.py
pygan/generativemodel/conditional_generative_model.py
pygan/generativemodel/deconvolution_model.py
pygan/generativemodel/encoder_decoder_model.py
pygan/generativemodel/lstm_model.py
pygan-1.0.9.dist-info/METADATA
pygan-1.0.9.dist-info/RECORD
pygan-1.0.9.dist-info/WHEEL
pygan-1.0.9.dist-info/top_level.txt
