Metadata-Version: 2.1
Name: pygan
Version: 1.0.9
Summary: pygan is Python library to implement Generative Adversarial Networks(GANs), Conditional GANs, Adversarial Auto-Encoders(AAEs), and Energy-based Generative Adversarial Network(EBGAN).
Home-page: https://github.com/accel-brain/accel-brain-code/tree/master/Generative-Adversarial-Networks/
Author: accel-brain
Author-email: info@accel-brain.co.jp
License: GPL2
Keywords: Generative Adversarial Networks Adversarial Auto-Encoders autoencoder auto-encoder convolution deconvolution encoder decoder LSTM
Platform: UNKNOWN
Classifier: Development Status :: 5 - Production/Stable
Classifier: Intended Audience :: Information Technology
Classifier: Intended Audience :: Science/Research
Classifier: Framework :: Robot Framework
Classifier: Topic :: Scientific/Engineering :: Artificial Intelligence
Classifier: License :: OSI Approved :: GNU General Public License v2 (GPLv2)
Classifier: Programming Language :: Python :: 3
Requires-Dist: numpy
Requires-Dist: accel-brain-base
